{
  "meta": {
    "image": "TextureAtlas_Buildings_1.png",
    "imageWidth": 1024,
    "imageHeight": 1024,
    "columns": 10,
    "rows": 10,
    "tileSize": 102.4,
    "origin": "top-left",
    "ordering": "row-major"
  },
  "sprites": [
    { "index": 0, "name": "Palisade Foundation" },
    { "index": 1, "name": "Palisade Wall" },
    { "index": 2, "name": "Palisade Window Wall" },
    { "index": 3, "name": "Palisade Floor" },
    { "index": 4, "name": "Palisade Roof" },
    { "index": 5, "name": "Doorframe" },
    { "index": 6, "name": "Reinforced Door (Basic)" },
    { "index": 7, "name": "Simple Lock (Keyed)" },
    { "index": 8, "name": "Hatch (Ceiling Access)" },
    { "index": 9, "name": "Spike Trap" },

    { "index": 10, "name": "Tripwire Alarm (Rope)" },
    { "index": 11, "name": "Smoke Trap (Defensive)" },
    { "index": 12, "name": "Workbench (Upgrade I)" },
    { "index": 13, "name": "Smelter (Starter)" },
    { "index": 14, "name": "Loom (Fiber)" },
    { "index": 15, "name": "Cooking Hearth" },
    { "index": 16, "name": "Storage Chest (Small)" },
    { "index": 17, "name": "Storage Chest (Large)" },
    { "index": 18, "name": "Camp Light" },
    { "index": 19, "name": "Water Catcher" },

    { "index": 20, "name": "Reinforced Foundation" },
    { "index": 21, "name": "Reinforced Wall" },
    { "index": 22, "name": "Reinforced Window Wall" },
    { "index": 23, "name": "Reinforced Floor" },
    { "index": 24, "name": "Reinforced Roof" },
    { "index": 25, "name": "Gate (Two‑panel)" },
    { "index": 26, "name": "Metal Door (Basic)" },
    { "index": 27, "name": "Code Lock (Prototype)" },
    { "index": 28, "name": "Garage Hatch" },
    { "index": 29, "name": "Window Shutter" },

    { "index": 30, "name": "Bear Trap" },
    { "index": 31, "name": "Barbed Tripline" },
    { "index": 32, "name": "Spike Trap (Reinforced)" },
    { "index": 33, "name": "Decoy Noisemaker" },
    { "index": 34, "name": "Sentry Turret (Manual)" },
    { "index": 35, "name": "Searchlight" },
    { "index": 36, "name": "Battery (Basic)" },
    { "index": 37, "name": "Wiring Kit" },
    { "index": 38, "name": "Workshop II Upgrade" },
    { "index": 39, "name": "Sawmill" },

    { "index": 40, "name": "Stone‑Plated Foundation" },
    { "index": 41, "name": "Stone‑Plated Wall" },
    { "index": 42, "name": "Embrasure (Arrow Slot)" },
    { "index": 43, "name": "Catwalk (Wall‑Top)" },
    { "index": 44, "name": "Vault Room Frame" },
    { "index": 45, "name": "Vault Door (Basic)" },
    { "index": 46, "name": "Reinforced Gate (Portcullis)" },
    { "index": 47, "name": "Roof Hatch (Armored)" },
    { "index": 48, "name": "Lock System (Reinforced)" },
    { "index": 49, "name": "Arrow Turret" },

    { "index": 50, "name": "Shot Trap (Prototype)" },
    { "index": 51, "name": "Searchlight (Powered)" },
    { "index": 52, "name": "Pressure Plate Mine" },
    { "index": 53, "name": "Flame Canister Trap" },
    { "index": 54, "name": "Breach‑Delay Foam" },
    { "index": 55, "name": "Shock Trap (Arcane)" },
    { "index": 56, "name": "Power Generator (Basic)" },
    { "index": 57, "name": "Battery Bank (Improved)" },
    { "index": 58, "name": "Ammo Press (Prototype)" },
    { "index": 59, "name": "Repair Station" },

    { "index": 60, "name": "Ward‑Plated Wall" },
    { "index": 61, "name": "Ward‑Plated Foundation" },
    { "index": 62, "name": "Ward‑Plated Roof" },
    { "index": 63, "name": "Ward‑Plated Gate" },
    { "index": 64, "name": "Vault Door (Reinforced)" },
    { "index": 65, "name": "Roof Hatch (Fortress)" },
    { "index": 66, "name": "Ballista Turret" },
    { "index": 67, "name": "Flak Turret (Anti‑Siege)" },
    { "index": 68, "name": "Searchlight (Fortress)" },
    { "index": 69, "name": "Breach Foam (Advanced)" },

    { "index": 70, "name": "Shock Trap (Fortress)" },
    { "index": 71, "name": "Smoke Trap (Anti‑Siege)" },
    { "index": 72, "name": "Power Generator (Fortress)" },
    { "index": 73, "name": "Power Core Housing" },
    { "index": 74, "name": "Siege Workshop (Modules)" },
    { "index": 75, "name": "Wardwork Table" },
    { "index": 76, "name": "Anti‑Breach Ward" },
    { "index": 77, "name": "Siege Shield Projector (Prototype)" },
    { "index": 78, "name": "Wall Patch Kit (Fortress)" },
    { "index": 79, "name": "Void‑Plated Wall" },

    { "index": 80, "name": "Void Roof (Sealed)" },
    { "index": 81, "name": "Void‑Reinforced Gate" },
    { "index": 82, "name": "Rift Hatch (Sealed)" },
    { "index": 83, "name": "Vault Lock (Void)" },
    { "index": 84, "name": "Void Airlock Door" },
    { "index": 85, "name": "Arcane Power Core" },
    { "index": 86, "name": "Power Router (Void)" },
    { "index": 87, "name": "Battery Bank (Void)" },
    { "index": 88, "name": "Riftwatch Turret" },
    { "index": 89, "name": "Nullbeam Projector" },

    { "index": 90, "name": "Rift Sensor Array" },
    { "index": 91, "name": "Blink Trap (Prototype)" },
    { "index": 92, "name": "Nullbloom Gas Trap" },
    { "index": 93, "name": "Phase Net (Prototype)" },
    { "index": 94, "name": "Voidforge Station" },
    { "index": 95, "name": "Riftwork Fabricator" },
    { "index": 96, "name": "Void Repair Station" },
    { "index": 97, "name": "Extraction Beacon (Base)" },
    { "index": 98, "name": "Rift Shield Projector" }
  ]
}